{"assets":[],"layers":[{"ddd":0,"ind":0,"ty":4,"nm":"Shape Layer 4","td":1,"ks":{"o":{"k":100},"r":{"k":0},"p":{"k":[{"i":{"x":0.667,"y":1},"o":{"x":0.333,"y":0},"n":"0p667_1_0p333_0","t":324,"s":[205,9,0],"e":[205,224,0],"to":[0,35.8333320617676,0],"ti":[0,-35.8333320617676,0]},{"t":344}],"x":"var $bm_rt;\nfunction easeandwizz_outBounce(t, b, c, d) {\n    if ((t /= d) < 1 / 2.75) {\n        return sum(mul(c, mul(mul(7.5625, t), t)), b);\n    } else if (t < 2 / 2.75) {\n        return sum(mul(c, sum(mul(mul(7.5625, t -= 1.5 / 2.75), t), 0.75)), b);\n    } else if (t < 2.5 / 2.75) {\n        return sum(mul(c, sum(mul(mul(7.5625, t -= 2.25 / 2.75), t), 0.9375)), b);\n    } else {\n        return sum(mul(c, sum(mul(mul(7.5625, t -= 2.625 / 2.75), t), 0.984375)), b);\n    }\n}\nfunction easeAndWizz() {\n    var t, d, sX, eX;\n    var n = 0;\n    if (numKeys > 0) {\n        n = nearestKey(time).index;\n        if (key(n).time > time) {\n            n--;\n        }\n    }\n    try {\n        var key1 = key(n);\n        var key2 = key(sum(n, 1));\n    } catch (e) {\n        return null;\n    }\n    var dim = 1;\n    try {\n        key(1)[1].length;\n        dim = 2;\n        key(1)[2].length;\n        dim = 3;\n    } catch (e) {\n    }\n    t = sub(time, key1.time);\n    d = sub(key2.time, key1.time);\n    sX = key1[0];\n    eX = sub(key2[0], key1[0]);\n    if (dim >= 2) {\n        sY = key1[1];\n        eY = sub(key2[1], key1[1]);\n        if (dim >= 3) {\n            sZ = key1[2];\n            eZ = sub(key2[2], key1[2]);\n        }\n    }\n    if (time < key1.time || time > key2.time) {\n        return value;\n    } else {\n        val1 = easeandwizz_outBounce(t, sX, eX, d);\n        switch (dim) {\n        case 1:\n            return val1;\n            break;\n        case 2:\n            val2 = easeandwizz_outBounce(t, sY, eY, d);\n            return [\n                val1,\n                val2\n            ];\n            break;\n        case 3:\n            val2 = easeandwizz_outBounce(t, sY, eY, d);\n            val3 = easeandwizz_outBounce(t, sZ, eZ, d);\n            return [\n                val1,\n                val2,\n                val3\n            ];\n            break;\n        default:\n            return null;\n        }\n    }\n}\n$bm_rt = easeAndWizz() || value;"},"a":{"k":[-102.564,-87.179,0]},"s":{"k":[{"i":{"x":[0.833,0.833,0.833],"y":[0.833,0.833,0.833]},"o":{"x":[0.167,0.167,0.167],"y":[0.167,0.167,0.167]},"n":["0p833_0p833_0p167_0p167","0p833_0p833_0p167_0p167","0p833_0p833_0p167_0p167"],"t":347,"s":[24,24,100],"e":[32,32,100]},{"i":{"x":[0.833,0.833,0.833],"y":[0.833,0.833,0.833]},"o":{"x":[0.167,0.167,0.167],"y":[0.167,0.167,0.167]},"n":["0p833_0p833_0p167_0p167","0p833_0p833_0p167_0p167","0p833_0p833_0p167_0p167"],"t":370,"s":[32,32,100],"e":[478,478,100]},{"t":376}]}},"ao":0,"shapes":[{"ty":"gr","it":[{"d":1,"ty":"el","s":{"k":[166,166]},"p":{"k":[0,0]},"nm":"Ellipse Path 1","mn":"ADBE Vector Shape - Ellipse"},{"ty":"st","fillEnabled":true,"c":{"k":[0.12,0.12,0.48,1]},"o":{"k":100},"w":{"k":0},"lc":1,"lj":1,"ml":4,"nm":"Stroke 1","mn":"ADBE Vector Graphic - Stroke"},{"ty":"fl","fillEnabled":true,"c":{"k":[0.94,0.93,0.9,1]},"o":{"k":100},"nm":"Fill 1","mn":"ADBE Vector Graphic - Fill"},{"ty":"tr","p":{"k":[-100,-94],"ix":2},"a":{"k":[0,0],"ix":1},"s":{"k":[100,100],"ix":3},"r":{"k":0,"ix":6},"o":{"k":100,"ix":7},"sk":{"k":0,"ix":4},"sa":{"k":0,"ix":5},"nm":"Transform"}],"nm":"Ellipse 1","np":3,"mn":"ADBE Vector Group"}],"ip":283,"op":918,"st":18,"bm":0,"sr":1},{"ddd":0,"ind":1,"ty":1,"nm":"Red Solid 1","tt":1,"ks":{"o":{"k":100},"r":{"k":0},"p":{"k":[203,210,0]},"a":{"k":[200,200,0]},"s":{"k":[109.5,109.5,100]}},"ao":0,"sw":400,"sh":400,"sc":"#f5093b","ip":325,"op":1003,"st":103,"bm":0,"sr":1},{"ddd":0,"ind":2,"ty":4,"nm":"Shape Layer 2","td":1,"ks":{"o":{"k":[{"i":{"x":[0.833],"y":[0.833]},"o":{"x":[0.167],"y":[0.167]},"n":["0p833_0p833_0p167_0p167"],"t":216,"s":[100],"e":[0]},{"i":{"x":[0.833],"y":[0.833]},"o":{"x":[0.167],"y":[0.167]},"n":["0p833_0p833_0p167_0p167"],"t":218,"s":[0],"e":[100]},{"i":{"x":[0.833],"y":[0.833]},"o":{"x":[0.167],"y":[0.167]},"n":["0p833_0p833_0p167_0p167"],"t":219,"s":[100],"e":[0]},{"i":{"x":[0.833],"y":[0.833]},"o":{"x":[0.167],"y":[0.167]},"n":["0p833_0p833_0p167_0p167"],"t":221,"s":[0],"e":[0]},{"i":{"x":[0.833],"y":[0.833]},"o":{"x":[0.167],"y":[0.167]},"n":["0p833_0p833_0p167_0p167"],"t":226,"s":[0],"e":[100]},{"i":{"x":[0.833],"y":[0.833]},"o":{"x":[0.167],"y":[0.167]},"n":["0p833_0p833_0p167_0p167"],"t":233,"s":[100],"e":[100]},{"i":{"x":[0.833],"y":[0.833]},"o":{"x":[0.167],"y":[0.167]},"n":["0p833_0p833_0p167_0p167"],"t":298,"s":[100],"e":[0]},{"t":303}]},"r":{"k":0},"p":{"k":[{"i":{"x":0.667,"y":1},"o":{"x":0.333,"y":0},"n":"0p667_1_0p333_0","t":232,"s":[206,214,0],"e":[28,43,0],"to":[-29.6666660308838,-28.5,0],"ti":[11,-27.1666660308838,0]},{"i":{"x":0.667,"y":1},"o":{"x":0.333,"y":0},"n":"0p667_1_0p333_0","t":233,"s":[28,43,0],"e":[67.2,241.733,0],"to":[-6.20691251754761,15.3291931152344,0],"ti":[-41.6137199401855,-79.9867706298828,0]},{"i":{"x":0.667,"y":1},"o":{"x":0.333,"y":0},"n":"0p667_1_0p333_0","t":241,"s":[67.2,241.733,0],"e":[346.563,76.274,0],"to":[26.4268913269043,50.795783996582,0],"ti":[-59.9289169311523,37.4352340698242,0]},{"i":{"x":0.667,"y":1},"o":{"x":0.333,"y":0},"n":"0p667_1_0p333_0","t":259,"s":[346.563,76.274,0],"e":[354.563,334.274,0],"to":[51.3920288085938,-32.1025733947754,0],"ti":[0,-3.66666674613953,0]},{"i":{"x":0.667,"y":1},"o":{"x":0.333,"y":0},"n":"0p667_1_0p333_0","t":278,"s":[354.563,334.274,0],"e":[24.563,44.274,0],"to":[0,3.66666674613953,0],"ti":[7,0,0]},{"t":297}]},"a":{"k":[-163.504,-159.124,0]},"s":{"k":[{"i":{"x":[0.833,0.833,0.833],"y":[0.833,0.833,0.833]},"o":{"x":[0.167,0.167,0.167],"y":[0.167,0.167,0.167]},"n":["0p833_0p833_0p167_0p167","0p833_0p833_0p167_0p167","0p833_0p833_0p167_0p167"],"t":232,"s":[199,199,100],"e":[124.64,124.64,100]},{"t":233}]}},"ao":0,"shapes":[{"ty":"gr","it":[{"d":1,"ty":"el","s":{"k":[266,266]},"p":{"k":[0,0]},"nm":"Ellipse Path 1","mn":"ADBE Vector Shape - Ellipse"},{"ty":"st","fillEnabled":true,"c":{"k":[0.12,0.12,0.48,1]},"o":{"k":100},"w":{"k":0},"lc":1,"lj":1,"ml":4,"nm":"Stroke 1","mn":"ADBE Vector Graphic - Stroke"},{"ty":"fl","fillEnabled":true,"c":{"k":[0.94,0.93,0.9,1]},"o":{"k":100},"nm":"Fill 1","mn":"ADBE Vector Graphic - Fill"},{"ty":"tr","p":{"k":[-159,-163],"ix":2},"a":{"k":[0,0],"ix":1},"s":{"k":[100,100],"ix":3},"r":{"k":0,"ix":6},"o":{"k":100,"ix":7},"sk":{"k":0,"ix":4},"sa":{"k":0,"ix":5},"nm":"Transform"}],"nm":"Ellipse 1","np":3,"mn":"ADBE Vector Group"}],"ip":216,"op":308,"st":216,"bm":0,"sr":1},{"ddd":0,"ind":3,"ty":4,"nm":"Shape Layer 3","tt":2,"ks":{"o":{"k":[{"i":{"x":[0.833],"y":[0.833]},"o":{"x":[0.167],"y":[0.167]},"n":["0p833_0p833_0p167_0p167"],"t":226,"s":[100],"e":[0]},{"i":{"x":[0.833],"y":[0.833]},"o":{"x":[0.167],"y":[0.167]},"n":["0p833_0p833_0p167_0p167"],"t":230,"s":[0],"e":[100]},{"i":{"x":[0.833],"y":[0.833]},"o":{"x":[0.167],"y":[0.167]},"n":["0p833_0p833_0p167_0p167"],"t":251,"s":[100],"e":[100]},{"i":{"x":[0.833],"y":[0.833]},"o":{"x":[0.167],"y":[0.167]},"n":["0p833_0p833_0p167_0p167"],"t":291,"s":[100],"e":[0]},{"i":{"x":[0.833],"y":[0.833]},"o":{"x":[0.167],"y":[0.167]},"n":["0p833_0p833_0p167_0p167"],"t":298,"s":[0],"e":[0]},{"t":371}]},"r":{"k":[{"i":{"x":[0.833],"y":[0.833]},"o":{"x":[0.167],"y":[0.167]},"n":["0p833_0p833_0p167_0p167"],"t":105,"s":[0],"e":[90]},{"i":{"x":[0.833],"y":[0.833]},"o":{"x":[0.167],"y":[0.167]},"n":["0p833_0p833_0p167_0p167"],"t":129,"s":[90],"e":[90]},{"i":{"x":[0.833],"y":[0.833]},"o":{"x":[0.167],"y":[0.167]},"n":["0p833_0p833_0p167_0p167"],"t":144,"s":[90],"e":[180]},{"t":164}],"x":"var $bm_rt;\nfunction easeandwizz_inoutExpo(t, b, c, d) {\n    var CORRECTION = 0.000976563;\n    var v;\n    if ((t /= d / 2) < 1) {\n        v = sub(Math.pow(2, mul(10, sub(t, 1))), CORRECTION);\n    } else {\n        v = sum(sum($bm_neg(Math.pow(2, mul(-10, sub(t, 1)))), 2), CORRECTION);\n    }\n    return sum(b, mul(div(v, 2), c));\n}\nfunction easeAndWizz() {\n    var t, d, sX, eX;\n    var n = 0;\n    if (numKeys > 0) {\n        n = nearestKey(time).index;\n        if (key(n).time > time) {\n            n--;\n        }\n    }\n    if (n > 1 && n < numKeys - 1) {\n        return null;\n    }\n    try {\n        var key1 = key(n);\n        var key2 = key(sum(n, 1));\n    } catch (e) {\n        return null;\n    }\n    t = sub(time, key1.time);\n    d = sub(key2.time, key1.time);\n    sX = key1.time;\n    eX = sub(key2.time, key1.time);\n    if (time < key1.time || time > key2.time) {\n        return null;\n    } else {\n        return valueAtTime(easeandwizz_inoutExpo(t, sX, eX, d));\n    }\n}\n$bm_rt = easeAndWizz() || value;"},"p":{"k":[{"i":{"x":0.833,"y":0.833},"o":{"x":0.167,"y":0.167},"n":"0p833_0p833_0p167_0p167","t":97,"s":[202,211,0],"e":[202,211,0],"to":[0,0,0],"ti":[0,0,0]},{"i":{"x":0.833,"y":0.833},"o":{"x":0.167,"y":0.167},"n":"0p833_0p833_0p167_0p167","t":111,"s":[202,211,0],"e":[202.125,211.125,0],"to":[0.02083333395422,0.02083333395422,0],"ti":[-0.02083333395422,-0.02083333395422,0]},{"t":179}]},"a":{"k":[-35,-9,0]},"s":{"k":[50,50,100]}},"ao":0,"shapes":[{"ty":"gr","it":[{"ty":"rc","d":2,"s":{"k":[{"i":{"x":[0.833,0.833],"y":[0.833,0.833]},"o":{"x":[0.167,0.167],"y":[0.167,0.167]},"n":["0p833_0p833_0p167_0p167","0p833_0p833_0p167_0p167"],"t":182,"s":[147,147],"e":[689,147]},{"i":{"x":[0.833,0.833],"y":[0.833,0.833]},"o":{"x":[0.167,0.167],"y":[0.167,0.167]},"n":["0p833_0p833_0p167_0p167","0p833_0p833_0p167_0p167"],"t":194,"s":[689,147],"e":[689,147]},{"i":{"x":[0.833,0.833],"y":[0.833,0.833]},"o":{"x":[0.167,0.167],"y":[0.167,0.167]},"n":["0p833_0p833_0p167_0p167","0p833_0p833_0p167_0p167"],"t":202,"s":[689,147],"e":[689,689]},{"t":214}],"x":"var $bm_rt;\nfunction easeandwizz_inoutQuart(t, b, c, d) {\n    if ((t /= d / 2) < 1)\n        return sum(mul(mul(mul(mul(div(c, 2), t), t), t), t), b);\n    return sum(mul(div($bm_neg(c), 2), sub(mul(mul(mul(t -= 2, t), t), t), 2)), b);\n}\nfunction easeAndWizz() {\n    var t, d, sX, eX;\n    var n = 0;\n    if (numKeys > 0) {\n        n = nearestKey(time).index;\n        if (key(n).time > time) {\n            n--;\n        }\n    }\n    if (n > 1 && n < numKeys - 1) {\n        return null;\n    }\n    try {\n        var key1 = key(n);\n        var key2 = key(sum(n, 1));\n    } catch (e) {\n        return null;\n    }\n    t = sub(time, key1.time);\n    d = sub(key2.time, key1.time);\n    sX = key1.time;\n    eX = sub(key2.time, key1.time);\n    if (time < key1.time || time > key2.time) {\n        return null;\n    } else {\n        return valueAtTime(easeandwizz_inoutQuart(t, sX, eX, d));\n    }\n}\n$bm_rt = easeAndWizz() || value;"},"p":{"k":[0,0]},"r":{"k":2},"nm":"Rectangle Path 1","mn":"ADBE Vector Shape - Rect"},{"ty":"st","fillEnabled":true,"c":{"k":[{"i":{"x":[0.833],"y":[0.833]},"o":{"x":[0.167],"y":[0.167]},"n":["0p833_0p833_0p167_0p167"],"t":18,"s":[0.96,0.04,0.23,1],"e":[1,0.7,0,1]},{"i":{"x":[0.833],"y":[0.833]},"o":{"x":[0.167],"y":[0.167]},"n":["0p833_0p833_0p167_0p167"],"t":28,"s":[1,0.7,0,1],"e":[0.09,1,0,1]},{"t":38}]},"o":{"k":100},"w":{"k":[{"i":{"x":[0.833],"y":[0.833]},"o":{"x":[0.167],"y":[0.167]},"n":["0p833_0p833_0p167_0p167"],"t":153,"s":[17],"e":[55]},{"i":{"x":[0.833],"y":[0.833]},"o":{"x":[0.167],"y":[0.167]},"n":["0p833_0p833_0p167_0p167"],"t":154,"s":[55],"e":[55]},{"i":{"x":[0.833],"y":[0.833]},"o":{"x":[0.167],"y":[0.167]},"n":["0p833_0p833_0p167_0p167"],"t":169,"s":[55],"e":[8]},{"i":{"x":[0.833],"y":[0.833]},"o":{"x":[0.167],"y":[0.167]},"n":["0p833_0p833_0p167_0p167"],"t":178,"s":[8],"e":[8]},{"t":183}],"x":"var $bm_rt;\nfunction easeandwizz_inoutQuart(t, b, c, d) {\n    if ((t /= d / 2) < 1)\n        return sum(mul(mul(mul(mul(div(c, 2), t), t), t), t), b);\n    return sum(mul(div($bm_neg(c), 2), sub(mul(mul(mul(t -= 2, t), t), t), 2)), b);\n}\nfunction easeAndWizz() {\n    var t, d, sX, eX;\n    var n = 0;\n    if (numKeys > 0) {\n        n = nearestKey(time).index;\n        if (key(n).time > time) {\n            n--;\n        }\n    }\n    if (n > 1 && n < numKeys - 1) {\n        return null;\n    }\n    try {\n        var key1 = key(n);\n        var key2 = key(sum(n, 1));\n    } catch (e) {\n        return null;\n    }\n    t = sub(time, key1.time);\n    d = sub(key2.time, key1.time);\n    sX = key1.time;\n    eX = sub(key2.time, key1.time);\n    if (time < key1.time || time > key2.time) {\n        return null;\n    } else {\n        return valueAtTime(easeandwizz_inoutQuart(t, sX, eX, d));\n    }\n}\n$bm_rt = easeAndWizz() || value;"},"lc":1,"lj":1,"ml":4,"nm":"Stroke 1","mn":"ADBE Vector Graphic - Stroke"},{"ty":"fl","fillEnabled":true,"c":{"k":[{"i":{"x":[0.833],"y":[0.833]},"o":{"x":[0.167],"y":[0.167]},"n":["0p833_0p833_0p167_0p167"],"t":18,"s":[0.96,0.03,0.23,1],"e":[1,0.7,0,1]},{"i":{"x":[0.833],"y":[0.833]},"o":{"x":[0.167],"y":[0.167]},"n":["0p833_0p833_0p167_0p167"],"t":28,"s":[1,0.7,0,1],"e":[0.09,1,0,1]},{"t":38}]},"o":{"k":[{"i":{"x":[0.833],"y":[0.833]},"o":{"x":[0.167],"y":[0.167]},"n":["0p833_0p833_0p167_0p167"],"t":113,"s":[100],"e":[0]},{"t":121}]},"nm":"Fill 1","mn":"ADBE Vector Graphic - Fill"},{"ty":"tr","p":{"k":[-36,-9.5],"ix":2},"a":{"k":[0,0],"ix":1},"s":{"k":[100,100],"ix":3},"r":{"k":0,"ix":6},"o":{"k":100,"ix":7},"sk":{"k":0,"ix":4},"sa":{"k":0,"ix":5},"nm":"Transform"}],"nm":"Rectangle 1","np":3,"mn":"ADBE Vector Group"}],"ip":216,"op":403,"st":18,"bm":0,"sr":1},{"ddd":0,"ind":4,"ty":4,"nm":"Shape Layer 1","ks":{"o":{"k":100},"r":{"k":[{"i":{"x":[0.833],"y":[0.833]},"o":{"x":[0.167],"y":[0.167]},"n":["0p833_0p833_0p167_0p167"],"t":105,"s":[0],"e":[90]},{"i":{"x":[0.833],"y":[0.833]},"o":{"x":[0.167],"y":[0.167]},"n":["0p833_0p833_0p167_0p167"],"t":129,"s":[90],"e":[90]},{"i":{"x":[0.833],"y":[0.833]},"o":{"x":[0.167],"y":[0.167]},"n":["0p833_0p833_0p167_0p167"],"t":144,"s":[90],"e":[180]},{"t":164}],"x":"var $bm_rt;\nfunction easeandwizz_inoutExpo(t, b, c, d) {\n    var CORRECTION = 0.000976563;\n    var v;\n    if ((t /= d / 2) < 1) {\n        v = sub(Math.pow(2, mul(10, sub(t, 1))), CORRECTION);\n    } else {\n        v = sum(sum($bm_neg(Math.pow(2, mul(-10, sub(t, 1)))), 2), CORRECTION);\n    }\n    return sum(b, mul(div(v, 2), c));\n}\nfunction easeAndWizz() {\n    var t, d, sX, eX;\n    var n = 0;\n    if (numKeys > 0) {\n        n = nearestKey(time).index;\n        if (key(n).time > time) {\n            n--;\n        }\n    }\n    if (n > 1 && n < numKeys - 1) {\n        return null;\n    }\n    try {\n        var key1 = key(n);\n        var key2 = key(sum(n, 1));\n    } catch (e) {\n        return null;\n    }\n    t = sub(time, key1.time);\n    d = sub(key2.time, key1.time);\n    sX = key1.time;\n    eX = sub(key2.time, key1.time);\n    if (time < key1.time || time > key2.time) {\n        return null;\n    } else {\n        return valueAtTime(easeandwizz_inoutExpo(t, sX, eX, d));\n    }\n}\n$bm_rt = easeAndWizz() || value;"},"p":{"k":[{"i":{"x":0.833,"y":0.833},"o":{"x":0.167,"y":0.167},"n":"0p833_0p833_0p167_0p167","t":30,"s":[202,211,0],"e":[202,194.5,0],"to":[0,0,0],"ti":[0,-2.75,0]},{"i":{"x":0.833,"y":0.833},"o":{"x":0.167,"y":0.167},"n":"0p833_0p833_0p167_0p167","t":31,"s":[202,194.5,0],"e":[202,219.989,0],"to":[0,0.14190359413624,0],"ti":[0,-0.1835709810257,0]},{"i":{"x":0.833,"y":0.833},"o":{"x":0.167,"y":0.167},"n":"0p833_0p833_0p167_0p167","t":32,"s":[202,219.989,0],"e":[202,194.5,0],"to":[0,3.3739161491394,0],"ti":[0,-2.75,0]},{"i":{"x":0.833,"y":0.833},"o":{"x":0.167,"y":0.167},"n":"0p833_0p833_0p167_0p167","t":33,"s":[202,194.5,0],"e":[202,219.989,0],"to":[0,0.14190359413624,0],"ti":[0,-0.1835709810257,0]},{"i":{"x":0.833,"y":0.833},"o":{"x":0.167,"y":0.167},"n":"0p833_0p833_0p167_0p167","t":34,"s":[202,219.989,0],"e":[202,194.5,0],"to":[0,3.3739161491394,0],"ti":[0,-2.75,0]},{"i":{"x":0.833,"y":0.833},"o":{"x":0.167,"y":0.167},"n":"0p833_0p833_0p167_0p167","t":35,"s":[202,194.5,0],"e":[202,211,0],"to":[0,0.14190359413624,0],"ti":[0,-2.60809636116028,0]},{"i":{"x":0.833,"y":0.833},"o":{"x":0.167,"y":0.167},"n":"0p833_0p833_0p167_0p167","t":36,"s":[202,211,0],"e":[202,211,0],"to":[0,0,0],"ti":[0,0,0]},{"i":{"x":0.941,"y":1},"o":{"x":0.182,"y":1},"n":"0p941_1_0p182_1","t":51,"s":[202,211,0],"e":[247,211,0],"to":[0,0,0],"ti":[0,0,0]},{"i":{"x":0.833,"y":0.833},"o":{"x":0.333,"y":0.017},"n":"0p833_0p833_0p333_0p017","t":81,"s":[247,211,0],"e":[188,211,0],"to":[0,0,0],"ti":[0,0,0]},{"i":{"x":0.833,"y":0.833},"o":{"x":0.167,"y":0.167},"n":"0p833_0p833_0p167_0p167","t":83,"s":[188,211,0],"e":[202,211,0],"to":[0,0,0],"ti":[0,0,0]},{"i":{"x":0.833,"y":0.833},"o":{"x":0.167,"y":0.167},"n":"0p833_0p833_0p167_0p167","t":85,"s":[202,211,0],"e":[202,211,0],"to":[0,0,0],"ti":[0,0,0]},{"i":{"x":0.833,"y":0.833},"o":{"x":0.167,"y":0.167},"n":"0p833_0p833_0p167_0p167","t":111,"s":[202,211,0],"e":[202.125,211.125,0],"to":[0.02083333395422,0.02083333395422,0],"ti":[-0.02083333395422,-0.02083333395422,0]},{"t":179}],"x":"var $bm_rt;\nfunction easeandwizz_inoutExpo(t, b, c, d) {\n    var CORRECTION = 0.000976563;\n    var v;\n    if ((t /= d / 2) < 1) {\n        v = sub(Math.pow(2, mul(10, sub(t, 1))), CORRECTION);\n    } else {\n        v = sum(sum($bm_neg(Math.pow(2, mul(-10, sub(t, 1)))), 2), CORRECTION);\n    }\n    return sum(b, mul(div(v, 2), c));\n}\nfunction easeAndWizz() {\n    var t, d, sX, eX;\n    var n = 0;\n    if (numKeys > 0) {\n        n = nearestKey(time).index;\n        if (key(n).time > time) {\n            n--;\n        }\n    }\n    if (n > 1 && n < numKeys - 1) {\n        return null;\n    }\n    try {\n        var key1 = key(n);\n        var key2 = key(sum(n, 1));\n    } catch (e) {\n        return null;\n    }\n    t = sub(time, key1.time);\n    d = sub(key2.time, key1.time);\n    sX = key1.time;\n    eX = sub(key2.time, key1.time);\n    if (time < key1.time || time > key2.time) {\n        return null;\n    } else {\n        return valueAtTime(easeandwizz_inoutExpo(t, sX, eX, d));\n    }\n}\n$bm_rt = easeAndWizz() || value;"},"a":{"k":[-35,-9,0]},"s":{"k":[{"i":{"x":[0.833,0.833,0.833],"y":[0.833,0.833,0.833]},"o":{"x":[0.167,0.167,0.167],"y":[0.167,0.167,0.167]},"n":["0p833_0p833_0p167_0p167","0p833_0p833_0p167_0p167","0p833_0p833_0p167_0p167"],"t":0,"s":[284,284,100],"e":[50,50,100]},{"t":16}],"x":"var $bm_rt;\nfunction easeandwizz_inoutExpo(t, b, c, d) {\n    var CORRECTION = 0.000976563;\n    var v;\n    if ((t /= d / 2) < 1) {\n        v = sub(Math.pow(2, mul(10, sub(t, 1))), CORRECTION);\n    } else {\n        v = sum(sum($bm_neg(Math.pow(2, mul(-10, sub(t, 1)))), 2), CORRECTION);\n    }\n    return sum(b, mul(div(v, 2), c));\n}\nfunction easeAndWizz() {\n    var t, d, sX, eX;\n    var n = 0;\n    if (numKeys > 0) {\n        n = nearestKey(time).index;\n        if (key(n).time > time) {\n            n--;\n        }\n    }\n    if (n > 1 && n < numKeys - 1) {\n        return null;\n    }\n    try {\n        var key1 = key(n);\n        var key2 = key(sum(n, 1));\n    } catch (e) {\n        return null;\n    }\n    var dim = 1;\n    try {\n        key(1)[1].length;\n        dim = 2;\n        key(1)[2].length;\n        dim = 3;\n    } catch (e) {\n    }\n    t = sub(time, key1.time);\n    d = sub(key2.time, key1.time);\n    sX = key1[0];\n    eX = sub(key2[0], key1[0]);\n    if (dim >= 2) {\n        sY = key1[1];\n        eY = sub(key2[1], key1[1]);\n        if (dim >= 3) {\n            sZ = key1[2];\n            eZ = sub(key2[2], key1[2]);\n        }\n    }\n    if (time < key1.time || time > key2.time) {\n        return value;\n    } else {\n        val1 = easeandwizz_inoutExpo(t, sX, eX, d);\n        switch (dim) {\n        case 1:\n            return val1;\n            break;\n        case 2:\n            val2 = easeandwizz_inoutExpo(t, sY, eY, d);\n            return [\n                val1,\n                val2\n            ];\n            break;\n        case 3:\n            val2 = easeandwizz_inoutExpo(t, sY, eY, d);\n            val3 = easeandwizz_inoutExpo(t, sZ, eZ, d);\n            return [\n                val1,\n                val2,\n                val3\n            ];\n            break;\n        default:\n            return null;\n        }\n    }\n}\n$bm_rt = easeAndWizz() || value;"}},"ao":0,"shapes":[{"ty":"gr","it":[{"ty":"rc","d":2,"s":{"k":[{"i":{"x":[0.833,0.833],"y":[0.833,0.833]},"o":{"x":[0.167,0.167],"y":[0.167,0.167]},"n":["0p833_0p833_0p167_0p167","0p833_0p833_0p167_0p167"],"t":182,"s":[147,147],"e":[689,147]},{"i":{"x":[0.833,0.833],"y":[0.833,0.833]},"o":{"x":[0.167,0.167],"y":[0.167,0.167]},"n":["0p833_0p833_0p167_0p167","0p833_0p833_0p167_0p167"],"t":194,"s":[689,147],"e":[689,147]},{"i":{"x":[0.833,0.833],"y":[0.833,0.833]},"o":{"x":[0.167,0.167],"y":[0.167,0.167]},"n":["0p833_0p833_0p167_0p167","0p833_0p833_0p167_0p167"],"t":202,"s":[689,147],"e":[689,689]},{"t":214}],"x":"var $bm_rt;\nfunction easeandwizz_inoutQuart(t, b, c, d) {\n    if ((t /= d / 2) < 1)\n        return sum(mul(mul(mul(mul(div(c, 2), t), t), t), t), b);\n    return sum(mul(div($bm_neg(c), 2), sub(mul(mul(mul(t -= 2, t), t), t), 2)), b);\n}\nfunction easeAndWizz() {\n    var t, d, sX, eX;\n    var n = 0;\n    if (numKeys > 0) {\n        n = nearestKey(time).index;\n        if (key(n).time > time) {\n            n--;\n        }\n    }\n    if (n > 1 && n < numKeys - 1) {\n        return null;\n    }\n    try {\n        var key1 = key(n);\n        var key2 = key(sum(n, 1));\n    } catch (e) {\n        return null;\n    }\n    t = sub(time, key1.time);\n    d = sub(key2.time, key1.time);\n    sX = key1.time;\n    eX = sub(key2.time, key1.time);\n    if (time < key1.time || time > key2.time) {\n        return null;\n    } else {\n        return valueAtTime(easeandwizz_inoutQuart(t, sX, eX, d));\n    }\n}\n$bm_rt = easeAndWizz() || value;"},"p":{"k":[0,0]},"r":{"k":2},"nm":"Rectangle Path 1","mn":"ADBE Vector Shape - Rect"},{"ty":"st","fillEnabled":true,"c":{"k":[{"i":{"x":[0.833],"y":[0.833]},"o":{"x":[0.167],"y":[0.167]},"n":["0p833_0p833_0p167_0p167"],"t":31,"s":[0.96,0.04,0.23,1],"e":[1,0.7,0,1]},{"i":{"x":[0.833],"y":[0.833]},"o":{"x":[0.167],"y":[0.167]},"n":["0p833_0p833_0p167_0p167"],"t":37,"s":[1,0.7,0,1],"e":[1,0.7,0,1]},{"i":{"x":[0.833],"y":[0.833]},"o":{"x":[0.167],"y":[0.167]},"n":["0p833_0p833_0p167_0p167"],"t":81,"s":[1,0.7,0,1],"e":[0.09,1,0,1]},{"t":82}]},"o":{"k":100},"w":{"k":[{"i":{"x":[0.833],"y":[0.833]},"o":{"x":[0.167],"y":[0.167]},"n":["0p833_0p833_0p167_0p167"],"t":153,"s":[17],"e":[55]},{"i":{"x":[0.833],"y":[0.833]},"o":{"x":[0.167],"y":[0.167]},"n":["0p833_0p833_0p167_0p167"],"t":154,"s":[55],"e":[55]},{"i":{"x":[0.833],"y":[0.833]},"o":{"x":[0.167],"y":[0.167]},"n":["0p833_0p833_0p167_0p167"],"t":169,"s":[55],"e":[8]},{"i":{"x":[0.833],"y":[0.833]},"o":{"x":[0.167],"y":[0.167]},"n":["0p833_0p833_0p167_0p167"],"t":178,"s":[8],"e":[8]},{"t":183}],"x":"var $bm_rt;\nfunction easeandwizz_inoutQuart(t, b, c, d) {\n    if ((t /= d / 2) < 1)\n        return sum(mul(mul(mul(mul(div(c, 2), t), t), t), t), b);\n    return sum(mul(div($bm_neg(c), 2), sub(mul(mul(mul(t -= 2, t), t), t), 2)), b);\n}\nfunction easeAndWizz() {\n    var t, d, sX, eX;\n    var n = 0;\n    if (numKeys > 0) {\n        n = nearestKey(time).index;\n        if (key(n).time > time) {\n            n--;\n        }\n    }\n    if (n > 1 && n < numKeys - 1) {\n        return null;\n    }\n    try {\n        var key1 = key(n);\n        var key2 = key(sum(n, 1));\n    } catch (e) {\n        return null;\n    }\n    t = sub(time, key1.time);\n    d = sub(key2.time, key1.time);\n    sX = key1.time;\n    eX = sub(key2.time, key1.time);\n    if (time < key1.time || time > key2.time) {\n        return null;\n    } else {\n        return valueAtTime(easeandwizz_inoutQuart(t, sX, eX, d));\n    }\n}\n$bm_rt = easeAndWizz() || value;"},"lc":1,"lj":1,"ml":4,"nm":"Stroke 1","mn":"ADBE Vector Graphic - Stroke"},{"ty":"fl","fillEnabled":true,"c":{"k":[{"i":{"x":[0.833],"y":[0.833]},"o":{"x":[0.167],"y":[0.167]},"n":["0p833_0p833_0p167_0p167"],"t":31,"s":[0.96,0.03,0.23,1],"e":[1,0.7,0,1]},{"i":{"x":[0.833],"y":[0.833]},"o":{"x":[0.167],"y":[0.167]},"n":["0p833_0p833_0p167_0p167"],"t":37,"s":[1,0.7,0,1],"e":[1,0.7,0,1]},{"i":{"x":[0.833],"y":[0.833]},"o":{"x":[0.167],"y":[0.167]},"n":["0p833_0p833_0p167_0p167"],"t":81,"s":[1,0.7,0,1],"e":[0.09,1,0,1]},{"t":82}]},"o":{"k":[{"i":{"x":[0.833],"y":[0.833]},"o":{"x":[0.167],"y":[0.167]},"n":["0p833_0p833_0p167_0p167"],"t":113,"s":[100],"e":[0]},{"t":121}]},"nm":"Fill 1","mn":"ADBE Vector Graphic - Fill"},{"ty":"tr","p":{"k":[-36,-9.5],"ix":2},"a":{"k":[0,0],"ix":1},"s":{"k":[100,100],"ix":3},"r":{"k":0,"ix":6},"o":{"k":100,"ix":7},"sk":{"k":0,"ix":4},"sa":{"k":0,"ix":5},"nm":"Transform"}],"nm":"Rectangle 1","np":3,"mn":"ADBE Vector Group"}],"ip":-11,"op":216,"st":18,"bm":0,"sr":1}],"v":"4.5.0","ddd":0,"ip":1,"op":378,"fr":30,"w":400,"h":400}